<Contactos>
  <Contacto>
    <direccion localidad="la linea">rosales</direccion>
    <telefono prefijo="esp">123</telefono>
    <nombreCont>Pepe</nombreCont>
    <codP>11300</codP>
    <deboMoney>true</deboMoney>
    <cantDeb moneda="€">10.2</cantDeb>
  </Contacto>
  <Contacto>
    <direccion localidad="NY">SanPedro</direccion>
    <telefono prefijo="EEUU">4578</telefono>
    <nombreCont>Juan</nombreCont>
    <codP>11300</codP>
    <deboMoney>false</deboMoney>
    <cantDeb moneda="$">0.0</cantDeb>
  </Contacto>
</Contactos>